[
    {
        "text": "Emitir palabras",
        "category": "Verbos",
        "answer": "HABLAR",
        "options": [],
        "isAnswer": true
    },
    {
        "text": "Tener vida",
        "category": "Verbos",
        "answer": "VIVIR",
        "options": [],
        "isAnswer": true
    },
    {
        "text": "Ejercitar el entendimiento para alcanzar o comprender algo",
        "category": "Verbos",
        "answer": "ESTUDIAR",
        "options": [],
        "isAnswer": true
    },
    {
        "text": "Ocuparse en cualquier actividad física o intelectual",
        "category": "Verbos",
        "answer": "TRABAJAR",
        "options": [],
        "isAnswer": true
    },
    {
        "text": "Andar determinada distancia",
        "category": "Verbos",
        "answer": "CAMINAR",
        "options": [],
        "isAnswer": true
    },
    {
        "text": "Representar las palabras o las ideas con letras u otros signos trazados en papel u otra superficie",
        "category": "Verbos", 
        "answer": "ESCRIBIR",
        "options": [],
        "isAnswer": true
    },
    "Sustantivos",
    "Adjetivos",
    "Preposiciones",
    {
        "text": "Dicho de una persona o de un animal: Trasladarse en el agua, ayudándose de los movimientos necesarios, y sin tocar el suelo ni otro apoyo",
        "category": "Verbos",
        "answer": "NADAR",
        "options": [],
        "isAnswer": true
    },
    {
        "text": "Ejecutar movimientos acompasados con el cuerpo, brazos y pies",
        "category": "Verbos",
        "answer": "BAILAR",
        "options": [],
        "isAnswer": true
    },
    {
        "text": "Adquirir el conocimiento de algo por medio del estudio o de la experiencia",
        "category": "Verbos",
        "answer": "APRENDER",
        "options": [],
        "isAnswer": true
    },
    {
        "text": "Dicho de una persona o de un animal: Andar rápidamente y con tanto impulso que, entre un paso y el siguiente, los pies o las patas quedan por un momento en el aire",
        "category": "Verbos",
        "answer": "CORRER",
        "options": [],
        "isAnswer": true
    }
]